dolistparser/__init__.py
dolistparser/__main__.py
dolistparser/_internal/__init__.py
dolistparser/_internal/domain/comment.py
dolistparser/_internal/interfaces/api.py
dolistparser/_internal/parsers/base.py
dolistparser/_internal/parsers/javascript.py
dolistparser/_internal/parsers/javascript_gh.py
dolistparser/_internal/parsers/python.py
dolistparser/_internal/parsers/python_gh.py
dolistparser/_internal/utils.py
dolistparser-0.2.2.dist-info/WHEEL
dolistparser-0.2.2.dist-info/METADATA
dolistparser-0.2.2.dist-info/RECORD
