Metadata-Version: 2.1
Name: dolistparser
Version: 0.2.2
Summary: Parse to-dos from the comment
Author: yunjae
Author-email: yunjae.oh.nl@gmail.com
Requires-Python: >=3.8,<4.0
Classifier: Programming Language :: Python :: 3
Classifier: Programming Language :: Python :: 3.10
Classifier: Programming Language :: Python :: 3.8
Classifier: Programming Language :: Python :: 3.9
Requires-Dist: pydantic (>=1.9.1,<2.0.0)
